Metadata-Version: 2.1
Name: RequestClient
Version: 0.4.0
Summary: Easy-to-use and convenient request wrapper that saves coding time. For Rest Request
Home-page: https://github.com/Randy341/RequestClient
Author: Randy Chang
Author-email: randy@randy-chang.com
License: MIT
Download-URL: https://github.com/Randy341/RequestClient/archive/0.4.0.tar.gz
Keywords: requests,HTTP,wrapper,client,REST
Platform: UNKNOWN
Classifier: Development Status :: 3 - Alpha
Classifier: Intended Audience :: Developers
Classifier: Topic :: Software Development :: Build Tools
Classifier: License :: OSI Approved :: MIT License
Classifier: Programming Language :: Python :: 3
Classifier: Programming Language :: Python :: 3.4
Classifier: Programming Language :: Python :: 3.5
Classifier: Programming Language :: Python :: 3.6
Classifier: Programming Language :: Python :: 3.7
